sheets_and_friends/__init__.py
sheets_and_friends/converters/__init__.py
sheets_and_friends/converters/sheet2linkml.py
sheets_and_friends/modifications_and_validation.py
sheets_and_friends/shuttle.py
sheets_and_friends-0.5.4.dist-info/METADATA
sheets_and_friends-0.5.4.dist-info/WHEEL
sheets_and_friends-0.5.4.dist-info/entry_points.txt
sheets_and_friends-0.5.4.dist-info/RECORD
