Metadata-Version: 2.1
Name: sheets_and_friends
Version: 0.5.4
Summary: Enhance a LinkML model with imported and optionally modified slots
License: MIT
Author: Mark Andrew Miller
Author-email: MAM@lbl.gov
Requires-Python: >=3.9,<4.0
Classifier: License :: OSI Approved :: MIT License
Classifier: Programming Language :: Python :: 3
Classifier: Programming Language :: Python :: 3.9
Classifier: Programming Language :: Python :: 3.10
Classifier: Programming Language :: Python :: 3.11
Classifier: Programming Language :: Python :: 3.12
Requires-Dist: click (>=8.0.0,<9.0.0)
Requires-Dist: click_log (==0.4.0)
Requires-Dist: glom (>=23.1.1,<24.0.0)
Requires-Dist: linkml-runtime (>=1.4.0,<2.0.0)
Requires-Dist: pandas (>=1.3.4)
Requires-Dist: pandasql (>=0.7.3,<0.8.0)
Requires-Dist: pygsheets (>=2.0.5,<3.0.0)
